jkq/qcec/__init__.py
jkq/qcec/pyqcec.cp39-win_amd64.pyd
jkq.qcec-1.10.4.dist-info/LICENSE
jkq.qcec-1.10.4.dist-info/METADATA
jkq.qcec-1.10.4.dist-info/WHEEL
jkq.qcec-1.10.4.dist-info/top_level.txt
jkq.qcec-1.10.4.dist-info/RECORD
