Metadata-Version: 2.1
Name: jkq.qcec
Version: 1.10.4
Summary: QCEC - A JKQ tool for Quantum Circuit Equivalence Checking
Home-page: https://iic.jku.at/eda/research/quantum_verification
Author: Lukas Burgholzer
Author-email: lukas.burgholzer@jku.at
License: MIT
Project-URL: Source, https://github.com/iic-jku/qcec/
Project-URL: Tracker, https://github.com/iic-jku/qcec/issues
Project-URL: Research, https://iic.jku.at/eda/research/quantum_verification
Keywords: jkq quantum verification
Platform: UNKNOWN
Classifier: Development Status :: 5 - Production/Stable
Classifier: Programming Language :: Python :: 3
Classifier: Programming Language :: C++
Classifier: License :: OSI Approved :: MIT License
Classifier: Operating System :: Microsoft :: Windows
Classifier: Operating System :: MacOS
Classifier: Operating System :: POSIX :: Linux
Classifier: Intended Audience :: Science/Research
Classifier: Natural Language :: English
Classifier: Topic :: Scientific/Engineering :: Electronic Design Automation (EDA)
License-File: LICENSE
